Workbook

Sheet Inicio
A1: Sistema de Inventario Cocina y Bar
A3: Uso del archivo
A5: 1. Cargar productos en la hoja Productos.
A6: 2. Registrar ingresos por lote en Lotes_FIFO.
A7: 3. Registrar todos los ingresos, salidas, mermas, producción, ventas y traspasos en Movimientos.
A8: 4. Definir recetas e ingredientes para cocina y bar.
A9: 5. Revisar Stock_Actual y Dashboard para alertas de mínimos.
A10: 6. Crear solicitudes a bodega central en Solicitudes.
A11: Celdas amarillas son datos editables. Las hojas de stock y dashboard contienen fórmulas.

Sheet Productos
A1: Codigo | B1: Producto | C1: Area | D1: Categoria | E1: Unidad | F1: Stock_Minimo | G1: Proveedor | H1: Estado
A2: P001 | B2: Tomate pera | C2: Cocina | D2: Verduras | E2: kg | F2: 8 | G2: Bodega central | H2: Activo
A3: P002 | B3: Carne molida | C3: Cocina | D3: Carnes | E3: kg | F3: 5 | G3: Bodega central | H3: Activo
A4: P003 | B4: Salsa pomodoro producida | C4: Cocina | D4: Producción | E4: lt | F4: 3 | G4: Producción cocina | H4: Activo
A5: P004 | B5: Pisco 35° | C5: Bar | D5: Destilados | E5: ml | F5: 2500 | G5: Bodega central | H5: Activo
A6: P005 | B6: Jugo de limón | C6: Bar | D6: Mixología | E6: ml | F6: 1500 | G6: Bodega central | H6: Activo
A7: P006 | B7: Jarabe goma | C7: Bar | D7: Mixología | E7: ml | F7: 1000 | G7: Bodega central | H7: Activo

Sheet Lotes_FIFO
A1: Lote | B1: Codigo_Producto | C1: Bodega | D1: Cantidad_Inicial | E1: Costo_Unitario | F1: Vencimiento | G1: Observacion
A2: L001 | B2: P001 | C2: Bodega Transitoria Cocina | D2: 12 | E2: 1200 | F2: 2026-10-20 | G2: Ingreso inicial
A3: L002 | B3: P002 | C3: Bodega Transitoria Cocina | D3: 7 | E3: 6500 | F3: 2026-10-18 | G3: Ingreso inicial
A4: L003 | B4: P004 | C4: Bodega Transitoria Bar | D4: 5000 | E4: 5.8 | F4: 2028-01-01 | G4: Ingreso inicial
A5: L004 | B5: P005 | C5: Bodega Transitoria Bar | D5: 2000 | E5: 3.2 | F5: 2026-10-17 | G5: Ingreso inicial
A6: L005 | B6: P006 | C6: Bodega Transitoria Bar | D6: 1200 | E6: 2.4 | F6: 2027-03-01 | G6: Ingreso inicial

Sheet Movimientos
A1: ID | B1: Fecha | C1: Tipo | D1: Codigo_Producto | E1: Bodega | F1: Cantidad | G1: Costo_Unitario | H1: Observacion
A2: M001 | B2: 2026-10-13 | C2: Ingreso | D2: P001 | E2: Bodega Transitoria Cocina | F2: 12 | G2: 1200 | H2: Ingreso inicial
A3: M002 | B3: 2026-10-13 | C3: Ingreso | D3: P002 | E3: Bodega Transitoria Cocina | F3: 7 | G3: 6500 | H3: Ingreso inicial
A4: M003 | B4: 2026-10-13 | C4: Ingreso | D4: P004 | E4: Bodega Transitoria Bar | F4: 5000 | G4: 5.8 | H4: Ingreso inicial
A5: M004 | B5: 2026-10-13 | C5: Ingreso | D5: P005 | E5: Bodega Transitoria Bar | F5: 2000 | G5: 3.2 | H5: Ingreso inicial
A6: M005 | B6: 2026-10-13 | C6: Ingreso | D6: P006 | E6: Bodega Transitoria Bar | F6: 1200 | G6: 2.4 | H6: Ingreso inicial

Sheet Recetas
A1: Codigo_Receta | B1: Nombre_Receta | C1: Tipo | D1: Rendimiento | E1: Unidad_Rendimiento
A2: R001 | B2: Salsa pomodoro base | C2: Producción Cocina | D2: 5 | E2: lt
A3: R002 | B3: Pisco sour clásico | C3: Venta Bar | D3: 1 | E3: copa

Sheet Ingredientes_Receta
A1: Codigo_Receta | B1: Codigo_Producto | C1: Cantidad | D1: Unidad | E1: Bodega_Consumo
A2: R001 | B2: P001 | C2: 4 | D2: kg | E2: Bodega Transitoria Cocina
A3: R002 | B3: P004 | C3: 75 | D3: ml | E3: Bodega Transitoria Bar
A4: R002 | B4: P005 | C4: 30 | D4: ml | E4: Bodega Transitoria Bar
A5: R002 | B5: P006 | C5: 20 | D5: ml | E5: Bodega Transitoria Bar

Sheet Produccion
A1: ID | B1: Fecha | C1: Codigo_Receta | D1: Cantidad_Producida | E1: Producto_Final | F1: Observacion

Sheet Mermas
A1: ID | B1: Fecha | C1: Codigo_Producto | D1: Bodega | E1: Cantidad | F1: Motivo | G1: Observacion

Sheet Ventas_Bar
A1: ID | B1: Fecha | C1: Codigo_Receta | D1: Cantidad_Vendida | E1: Referencia

Sheet Solicitudes
A1: ID | B1: Fecha | C1: Area | D1: Codigo_Producto | E1: Cantidad_Solicitada | F1: Prioridad | G1: Motivo | H1: Estado

Sheet Stock_Actual
A1: Codigo | B1: Producto | C1: Unidad | D1: Stock_Total | E1: Stock_Central | F1: Stock_Cocina | G1: Stock_Bar | H1: Stock_Minimo | I1: Estado | J1: Pedido_Sugerido
A2: =IF(Productos!A2="","",Productos!A2) | B2: =IF(A2="","",Productos!B2) | C2: =IF(A2="","",Productos!E2) | D2: =IF(A2="","",SUMIFS(Movimientos!F:F,Movimientos!D:D,A2)) | E2: =IF(A2="","",SUMIFS(Movimientos!F:F,Movimientos!D:D,A2,Movimientos!E:E,"Bodega Central")) | F2: =IF(A2="","",SUMIFS(Movimientos!F:F,Movimientos!D:D,A2,Movimientos!E:E,"Bodega Transitoria Cocina")) | G2: =IF(A2="","",SUMIFS(Movimientos!F:F,Movimientos!D:D,A2,Movimientos!E:E,"Bodega Transitoria Bar")) | H2: =IF(A2="","",Productos!F2) | I2: =IF(A2="","",IF(D2<=0,"Sin stock",IF(D2<=H2,"Bajo mínimo","OK"))) | J2: =IF(A2="","",MAX(H2*2-D2,0))
A3: =IF(Productos!A3="","",Productos!A3) | B3: =IF(A3="","",Productos!B3) | C3: =IF(A3="","",Productos!E3) | D3: =IF(A3="","",SUMIFS(Movimientos!F:F,Movimientos!D:D,A3)) | E3: =IF(A3="","",SUMIFS(Movimientos!F:F,Movimientos!D:D,A3,Movimientos!E:E,"Bodega Central")) | F3: =IF(A3="","",SUMIFS(Movimientos!F:F,Movimientos!D:D,A3,Movimientos!E:E,"Bodega Transitoria Cocina")) | G3: =IF(A3="","",SUMIFS(Movimientos!F:F,Movimientos!D:D,A3,Movimientos!E:E,"Bodega Transitoria Bar")) | H3: =IF(A3="","",Productos!F3) | I3: =IF(A3="","",IF(D3<=0,"Sin stock",IF(D3<=H3,"Bajo mínimo","OK"))) | J3: =IF(A3="","",MAX(H3*2-D3,0))
A4: =IF(Productos!A4="","",Productos!A4) | B4: =IF(A4="","",Productos!B4) | C4: =IF(A4="","",Productos!E4) | D4: =IF(A4="","",SUMIFS(Movimientos!F:F,Movimientos!D:D,A4)) | E4: =IF(A4="","",SUMIFS(Movimientos!F:F,Movimientos!D:D,A4,Movimientos!E:E,"Bodega Central")) | F4: =IF(A4="","",SUMIFS(Movimientos!F:F,Movimientos!D:D,A4,Movimientos!E:E,"Bodega Transitoria Cocina")) | G4: =IF(A4="","",SUMIFS(Movimientos!F:F,Movimientos!D:D,A4,Movimientos!E:E,"Bodega Transitoria Bar")) | H4: =IF(A4="","",Productos!F4) | I4: =IF(A4="","",IF(D4<=0,"Sin stock",IF(D4<=H4,"Bajo mínimo","OK"))) | J4: =IF(A4="","",MAX(H4*2-D4,0))
A5: =IF(Productos!A5="","",Productos!A5) | B5: =IF(A5="","",Productos!B5) | C5: =IF(A5="","",Productos!E5) | D5: =IF(A5="","",SUMIFS(Movimientos!F:F,Movimientos!D:D,A5)) | E5: =IF(A5="","",SUMIFS(Movimientos!F:F,Movimientos!D:D,A5,Movimientos!E:E,"Bodega Central")) | F5: =IF(A5="","",SUMIFS(Movimientos!F:F,Movimientos!D:D,A5,Movimientos!E:E,"Bodega Transitoria Cocina")) | G5: =IF(A5="","",SUMIFS(Movimientos!F:F,Movimientos!D:D,A5,Movimientos!E:E,"Bodega Transitoria Bar")) | H5: =IF(A5="","",Productos!F5) | I5: =IF(A5="","",IF(D5<=0,"Sin stock",IF(D5<=H5,"Bajo mínimo","OK"))) | J5: =IF(A5="","",MAX(H5*2-D5,0))
A6: =IF(Productos!A6="","",Productos!A6) | B6: =IF(A6="","",Productos!B6) | C6: =IF(A6="","",Productos!E6) | D6: =IF(A6="","",SUMIFS(Movimientos!F:F,Movimientos!D:D,A6)) | E6: =IF(A6="","",SUMIFS(Movimientos!F:F,Movimientos!D:D,A6,Movimientos!E:E,"Bodega Central")) | F6: =IF(A6="","",SUMIFS(Movimientos!F:F,Movimientos!D:D,A6,Movimientos!E:E,"Bodega Transitoria Cocina")) | G6: =IF(A6="","",SUMIFS(Movimientos!F:F,Movimientos!D:D,A6,Movimientos!E:E,"Bodega Transitoria Bar")) | H6: =IF(A6="","",Productos!F6) | I6: =IF(A6="","",IF(D6<=0,"Sin stock",IF(D6<=H6,"Bajo mínimo","OK"))) | J6: =IF(A6="","",MAX(H6*2-D6,0))
A7: =IF(Productos!A7="","",Productos!A7) | B7: =IF(A7="","",Productos!B7) | C7: =IF(A7="","",Productos!E7) | D7: =IF(A7="","",SUMIFS(Movimientos!F:F,Movimientos!D:D,A7)) | E7: =IF(A7="","",SUMIFS(Movimientos!F:F,Movimientos!D:D,A7,Movimientos!E:E,"Bodega Central")) | F7: =IF(A7="","",SUMIFS(Movimientos!F:F,Movimientos!D:D,A7,Movimientos!E:E,"Bodega Transitoria Cocina")) | G7: =IF(A7="","",SUMIFS(Movimientos!F:F,Movimientos!D:D,A7,Movimientos!E:E,"Bodega Transitoria Bar")) | H7: =IF(A7="","",Productos!F7) | I7: =IF(A7="","",IF(D7<=0,"Sin stock",IF(D7<=H7,"Bajo mínimo","OK"))) | J7: =IF(A7="","",MAX(H7*2-D7,0))
A8: =IF(Productos!A8="","",Productos!A8) | B8: =IF(A8="","",Productos!B8) | C8: =IF(A8="","",Productos!E8) | D8: =IF(A8="","",SUMIFS(Movimientos!F:F,Movimientos!D:D,A8)) | E8: =IF(A8="","",SUMIFS(Movimientos!F:F,Movimientos!D:D,A8,Movimientos!E:E,"Bodega Central")) | F8: =IF(A8="","",SUMIFS(Movimientos!F:F,Movimientos!D:D,A8,Movimientos!E:E,"Bodega Transitoria Cocina")) | G8: =IF(A8="","",SUMIFS(Movimientos!F:F,Movimientos!D:D,A8,Movimientos!E:E,"Bodega Transitoria Bar")) | H8: =IF(A8="","",Productos!F8) | I8: =IF(A8="","",IF(D8<=0,"Sin stock",IF(D8<=H8,"Bajo mínimo","OK"))) | J8: =IF(A8="","",MAX(H8*2-D8,0))
A9: =IF(Productos!A9="","",Productos!A9) | B9: =IF(A9="","",Productos!B9) | C9: =IF(A9="","",Productos!E9) | D9: =IF(A9="","",SUMIFS(Movimientos!F:F,Movimientos!D:D,A9)) | E9: =IF(A9="","",SUMIFS(Movimientos!F:F,Movimientos!D:D,A9,Movimientos!E:E,"Bodega Central")) | F9: =IF(A9="","",SUMIFS(Movimientos!F:F,Movimientos!D:D,A9,Movimientos!E:E,"Bodega Transitoria Cocina")) | G9: =IF(A9="","",SUMIFS(Movimientos!F:F,Movimientos!D:D,A9,Movimientos!E:E,"Bodega Transitoria Bar")) | H9: =IF(A9="","",Productos!F9) | I9: =IF(A9="","",IF(D9<=0,"Sin stock",IF(D9<=H9,"Bajo mínimo","OK"))) | J9: =IF(A9="","",MAX(H9*2-D9,0))
A10: =IF(Productos!A10="","",Productos!A10) | B10: =IF(A10="","",Productos!B10) | C10: =IF(A10="","",Productos!E10) | D10: =IF(A10="","",SUMIFS(Movimientos!F:F,Movimientos!D:D,A10)) | E10: =IF(A10="","",SUMIFS(Movimientos!F:F,Movimientos!D:D,A10,Movimientos!E:E,"Bodega Central")) | F10: =IF(A10="","",SUMIFS(Movimientos!F:F,Movimientos!D:D,A10,Movimientos!E:E,"Bodega Transitoria Cocina")) | G10: =IF(A10="","",SUMIFS(Movimientos!F:F,Movimientos!D:D,A10,Movimientos!E:E,"Bodega Transitoria Bar")) | H10: =IF(A10="","",Productos!F10) | I10: =IF(A10="","",IF(D10<=0,"Sin stock",IF(D10<=H10,"Bajo mínimo","OK"))) | J10: =IF(A10="","",MAX(H10*2-D10,0))
A11: =IF(Productos!A11="","",Productos!A11) | B11: =IF(A11="","",Productos!B11) | C11: =IF(A11="","",Productos!E11) | D11: =IF(A11="","",SUMIFS(Movimientos!F:F,Movimientos!D:D,A11)) | E11: =IF(A11="","",SUMIFS(Movimientos!F:F,Movimientos!D:D,A11,Movimientos!E:E,"Bodega Central")) | F11: =IF(A11="","",SUMIFS(Movimientos!F:F,Movimientos!D:D,A11,Movimientos!E:E,"Bodega Transitoria Cocina")) | G11: =IF(A11="","",SUMIFS(Movimientos!F:F,Movimientos!D:D,A11,Movimientos!E:E,"Bodega Transitoria Bar")) | H11: =IF(A11="","",Productos!F11) | I11: =IF(A11="","",IF(D11<=0,"Sin stock",IF(D11<=H11,"Bajo mínimo","OK"))) | J11: =IF(A11="","",MAX(H11*2-D11,0))
A12: =IF(Productos!A12="","",Productos!A12) | B12: =IF(A12="","",Productos!B12) | C12: =IF(A12="","",Productos!E12) | D12: =IF(A12="","",SUMIFS(Movimientos!F:F,Movimientos!D:D,A12)) | E12: =IF(A12="","",SUMIFS(Movimientos!F:F,Movimientos!D:D,A12,Movimientos!E:E,"Bodega Central")) | F12: =IF(A12="","",SUMIFS(Movimientos!F:F,Movimientos!D:D,A12,Movimientos!E:E,"Bodega Transitoria Cocina")) | G12: =IF(A12="","",SUMIFS(Movimientos!F:F,Movimientos!D:D,A12,Movimientos!E:E,"Bodega Transitoria Bar")) | H12: =IF(A12="","",Productos!F12) | I12: =IF(A12="","",IF(D12<=0,"Sin stock",IF(D12<=H12,"Bajo mínimo","OK"))) | J12: =IF(A12="","",MAX(H12*2-D12,0))
A13: =IF(Productos!A13="","",Productos!A13) | B13: =IF(A13="","",Productos!B13) | C13: =IF(A13="","",Productos!E13) | D13: =IF(A13="","",SUMIFS(Movimientos!F:F,Movimientos!D:D,A13)) | E13: =IF(A13="","",SUMIFS(Movimientos!F:F,Movimientos!D:D,A13,Movimientos!E:E,"Bodega Central")) | F13: =IF(A13="","",SUMIFS(Movimientos!F:F,Movimientos!D:D,A13,Movimientos!E:E,"Bodega Transitoria Cocina")) | G13: =IF(A13="","",SUMIFS(Movimientos!F:F,Movimientos!D:D,A13,Movimientos!E:E,"Bodega Transitoria Bar")) | H13: =IF(A13="","",Productos!F13) | I13: =IF(A13="","",IF(D13<=0,"Sin stock",IF(D13<=H13,"Bajo mínimo","OK"))) | J13: =IF(A13="","",MAX(H13*2-D13,0))
... A101: =IF(Productos!A101="","",Productos!A101) | B101: =IF(A101="","",Productos!B101) | C101: =IF(A101="","",Productos!E101) | D101: =IF(A101="","",SUMIFS(Movimientos!F:F,Movimientos!D:D,A101)) | E101: =IF(A101="","",SUMIFS(Movimientos!F:F,Movimientos!D:D,A101,Movimientos!E:E,"Bodega Central")) | F101: =IF(A101="","",SUMIFS(Movimientos!F:F,Movimientos!D:D,A101,Movimientos!E:E,"Bodega Transitoria Cocina")) | G101: =IF(A101="","",SUMIFS(Movimientos!F:F,Movimientos!D:D,A101,Movimientos!E:E,"Bodega Transitoria Bar")) | H101: =IF(A101="","",Productos!F101) | I101: =IF(A101="","",IF(D101<=0,"Sin stock",IF(D101<=H101,"Bajo mínimo","OK"))) | J101: =IF(A101="","",MAX(H101*2-D101,0))

Sheet Dashboard
A1: Dashboard de inventario
A3: Total productos | B3: =COUNTA(Productos!A:A)-1
A4: Valor inventario estimado | B4: =SUMPRODUCT(Movimientos!F:F,Movimientos!G:G)
A5: Productos bajo mínimo | B5: =COUNTIF(Stock_Actual!I:I,"Bajo mínimo")
A6: Productos sin stock | B6: =COUNTIF(Stock_Actual!I:I,"Sin stock")
A7: Movimientos registrados | B7: =COUNTA(Movimientos!A:A)-1
A10: Revisión diaria sugerida
A11: Revisar productos bajo mínimo antes del servicio.
A12: Registrar mermas el mismo día que ocurren.
A13: Cargar ventas de bar por receta al cierre de turno.
A14: Solicitar reposición a bodega central cuando el pedido sugerido sea mayor a cero.
